zurich_parking/__init__.py
zurich_parking/__main__.py
zurich_parking/config.toml
zurich_parking/parking.py
zurich_parking/parking_helper.py
zurich_parking-1.0.2.dist-info/entry_points.txt
zurich_parking-1.0.2.dist-info/LICENSE
zurich_parking-1.0.2.dist-info/METADATA
zurich_parking-1.0.2.dist-info/WHEEL
zurich_parking-1.0.2.dist-info/RECORD
