Metadata-Version: 2.1
Name: zurich-parking
Version: 1.0.2
Summary: Get information on free parking spaces in Zurich.
Home-page: https://github.com/TechPreacher/zurich-parking
License: MIT
Author: Sascha Corti
Author-email: sascha@corti.com
Requires-Python: >=3.9
Classifier: License :: OSI Approved :: MIT License
Classifier: Programming Language :: Python :: 3
Classifier: Programming Language :: Python :: 3.9
Classifier: Programming Language :: Python :: 3.10
Classifier: Programming Language :: Python :: 3.11
Classifier: Programming Language :: Python :: 3.12
Requires-Dist: feedparser (>=6.0.8,<7.0.0)
Requires-Dist: tomli (>=2.0.1,<3.0.0)
